grpc_admin/__init__.py
grpcio_admin-1.76.0.dist-info/LICENSE
grpcio_admin-1.76.0.dist-info/METADATA
grpcio_admin-1.76.0.dist-info/WHEEL
grpcio_admin-1.76.0.dist-info/top_level.txt
grpcio_admin-1.76.0.dist-info/RECORD
