Metadata-Version: 2.1
Name: grpcio-admin
Version: 1.76.0
Summary: a collection of admin services
Home-page: https://grpc.io
Author: The gRPC Authors
Author-email: grpc-io@googlegroups.com
License: Apache License 2.0
Classifier: Development Status :: 5 - Production/Stable
Classifier: Programming Language :: Python
Classifier: Programming Language :: Python :: 3
Classifier: License :: OSI Approved :: Apache Software License
Requires-Python: >=3.9
License-File: LICENSE
Requires-Dist: grpcio-channelz >=1.76.0
Requires-Dist: grpcio-csds >=1.76.0
